dagster_insights_prerelease/__init__.py
dagster_insights_prerelease/dagster_insights_patched/__init__.py
dagster_insights_prerelease/dagster_insights_patched/errors.py
dagster_insights_prerelease/dagster_insights_patched/insights_utils.py
dagster_insights_prerelease/dagster_insights_patched/metrics_utils.py
dagster_insights_prerelease/dagster_insights_patched/query.py
dagster_insights_prerelease/dagster_insights_patched/bigquery/__init__.py
dagster_insights_prerelease/dagster_insights_patched/bigquery/bigquery_utils.py
dagster_insights_prerelease/dagster_insights_patched/bigquery/dbt_wrapper.py
dagster_insights_prerelease/dagster_insights_patched/bigquery/insights_bigquery_resource.py
dagster_insights_prerelease/dagster_insights_patched/snowflake/__init__.py
dagster_insights_prerelease/dagster_insights_patched/snowflake/dagster_snowflake_insights.py
dagster_insights_prerelease/dagster_insights_patched/snowflake/dbt_wrapper.py
dagster_insights_prerelease/dagster_insights_patched/snowflake/definitions.py
dagster_insights_prerelease/dagster_insights_patched/snowflake/insights_snowflake_resource.py
dagster_insights_prerelease/dagster_insights_patched/snowflake/snowflake_utils.py
dagster_insights-0.0.20.dist-info/LICENSE.md
dagster_insights-0.0.20.dist-info/METADATA
dagster_insights-0.0.20.dist-info/WHEEL
dagster_insights-0.0.20.dist-info/top_level.txt
dagster_insights-0.0.20.dist-info/RECORD
