Metadata-Version: 2.1
Name: dagster-insights
Version: 0.0.20
Summary: Latest pre-release patches for dagster_cloud.dagster_insights.
Author: Dagster Labs
License: Released under the same license as dagster-cloud: https://pypi.org/project/dagster-cloud/
License-File: LICENSE.md
Requires-Dist: dagster-cloud
